{
  "birthday": null,
  "adult": false,
  "biography": null,
  "homepage": null,
  "profile_path": "/AeGLykfdziKEpQ8NY2uTfE5Lril.jpg",
  "id": 618,
  "also_known_as": [],
  "deathday": null,
  "imdb_id": "nm0594488",
  "combined_credits": {
    "cast": [
      {
        "id": 24752,
        "media_type": "movie",
        "title": "Dragon Ball Z: Cooler's Revenge",
        "credit_id": "52fe44a7c3a368484e02f4ef",
        "release_date": "1991-07-20",
        "original_title": "Doragon bôru Z 5: Tobikkiri no saikyô tai saikyô",
        "adult": false,
        "poster_path": "/oOHhEkl0vwP5D4CRY2HI0i2JN4k.jpg",
        "character": "Muten, Roshi"
      },
      {
        "id": 34433,
        "media_type": "movie",
        "title": "Dragon Ball Z: Broly - The Legendary Super Saiyan",
        "credit_id": "52fe45649251416c91030a59",
        "release_date": "1993-03-06",
        "original_title": "Dragon Ball Z - Moetsukiro!! Nessen Ressen Chô-Gekisen",
        "adult": false,
        "poster_path": "/3eHIyNW0MqTsQtijfuFeGUXlH4m.jpg",
        "character": "Muten, Roshi"
      },
      {
        "id": 28609,
        "media_type": "movie",
        "title": "Dragon Ball Z: The Deadzone",
        "credit_id": "52fe45a5c3a368484e066dd7",
        "release_date": "1989-07-15",
        "original_title": "Dragon Ball Z - Ora no Gohan wo Kaese",
        "adult": false,
        "poster_path": "/vk7JNEDWAxpGrtPNLs8R7A4KfoS.jpg",
        "character": "Muten, Roshi"
      },
      {
        "id": 15371,
        "media_type": "movie",
        "title": "Lupin the Third: The Castle of Cagliostro",
        "credit_id": "52fe46529251416c75074a25",
        "release_date": "1979-12-15",
        "original_title": "Rupan sansei: Kariosutoro no shiro",
        "adult": false,
        "poster_path": "/dN1InfPfmgxLwxirsR0SBXRydm9.jpg",
        "character": "Gardener"
      },
      {
        "id": 39100,
        "media_type": "movie",
        "title": "Dragon Ball Z: The World's Strongest",
        "credit_id": "52fe46f99251416c91065edb",
        "release_date": "1990-03-10",
        "original_title": "Dragon Ball Z - Kono yo de ichiban tsuyoi yatsu",
        "adult": false,
        "poster_path": "/wNPFBES1uQjy6WGMhYzEjAgpcGV.jpg",
        "character": "Muten, Roshi"
      },
      {
        "id": 39101,
        "media_type": "movie",
        "title": "Dragon Ball Z: The Tree of Might",
        "credit_id": "52fe46f99251416c91065f79",
        "release_date": "1990-06-07",
        "original_title": "Dragon Ball Z - Chikyū Marugoto Chōkessen",
        "adult": false,
        "poster_path": "/j6eDLGiveYES7oCBfCylcHPWmSN.jpg",
        "character": "Muten, Roshi"
      },
      {
        "id": 39102,
        "media_type": "movie",
        "title": "Dragon Ball Z: Lord Slug",
        "credit_id": "52fe46f99251416c91065fe5",
        "release_date": "1991-03-19",
        "original_title": "Doragon bôru Z 4: Super Saiyajin da Son Gokû",
        "adult": false,
        "poster_path": "/fpYiu4ucym84t5sDSuWZdvHJqX.jpg",
        "character": "Muten Roshi"
      },
      {
        "id": 39103,
        "media_type": "movie",
        "title": "Dragon Ball Z: Return of Cooler",
        "credit_id": "52fe46f99251416c91066041",
        "release_date": "1992-03-07",
        "original_title": "Dragon Ball Z - Gekitotsu !! Hyaku-Oku Power no Senshi-tachi",
        "adult": false,
        "poster_path": "/gimv43mbQskjvST3za5dBBugPxI.jpg",
        "character": "Muten, Roshi"
      },
      {
        "id": 39104,
        "media_type": "movie",
        "title": "Dragon Ball Z: Super Android 13",
        "credit_id": "52fe46f99251416c91066081",
        "release_date": "1992-07-11",
        "original_title": "Dragon Ball Z - Kyokugen Battle !! San Dai Super Saiyajin",
        "adult": false,
        "poster_path": "/cckfz0ziau9LScZFXGm4BOZUxkT.jpg",
        "character": "Muten, Roshi"
      },
      {
        "id": 39105,
        "media_type": "movie",
        "title": "Dragonball Z: Bojack Unbound",
        "credit_id": "52fe46f99251416c91066107",
        "release_date": "1993-07-10",
        "original_title": "Dragonball Z - Ginga Giri-Giri !! Bucchigiri no sugoi yatsu",
        "adult": false,
        "poster_path": "/mLkJgqUsYfJDGT0ul4JjVpuV7kW.jpg",
        "character": "Muten, Roshi"
      },
      {
        "id": 39144,
        "media_type": "movie",
        "title": "Dragon Ball: Curse of the Blood Rubies",
        "credit_id": "52fe46fe9251416c910669e1",
        "release_date": "1986-12-20",
        "original_title": "Doragon Bōru: Shenron no Densetsu",
        "adult": false,
        "poster_path": "/ieZGCyJpralWTfjL14gkW1NST2g.jpg",
        "character": "Muten, Roshi"
      },
      {
        "id": 39145,
        "media_type": "movie",
        "title": "Dragon Ball: Sleeping Princess in Devil's Castle",
        "credit_id": "52fe46fe9251416c91066a37",
        "release_date": "1987-07-18",
        "original_title": "Dragon Ball: Sleeping Princess in Devil's Castle",
        "adult": false,
        "poster_path": "/6wT8HEMBClfrSG1qvBQMi2FdlWO.jpg",
        "character": "Muten, Roshi"
      },
      {
        "id": 81,
        "media_type": "movie",
        "title": "Nausicaä of the Valley of the Wind",
        "credit_id": "52fe4215c3a36847f8002833",
        "release_date": "1984-03-11",
        "original_title": "風の谷のナウシカ",
        "adult": false,
        "poster_path": "/y2rl0OkMfZHpBaQYPfSJmLMOxwp.jpg",
        "character": "Goru (Voice)"
      },
      {
        "id": 22679,
        "media_type": "movie",
        "title": "Arion",
        "credit_id": "53ef2be6c3a3685ae2000c90",
        "release_date": "1986-03-15",
        "original_title": "Arion",
        "adult": false,
        "poster_path": "/6kfw7ES4xXGcPe4soFNjJnjZeLk.jpg",
        "character": "Ethos"
      },
      {
        "id": 8909,
        "media_type": "tv",
        "episode_count": 78,
        "credit_id": "525793f1760ee36aaa70423d",
        "name": "Fang of the Sun Dougram",
        "poster_path": "/jNkttXKKkm0KoP0VTmmfbEkliF1.jpg",
        "original_name": "Fang of the Sun Dougram",
        "first_air_date": "1981-10-23",
        "character": "David"
      },
      {
        "id": 8962,
        "media_type": "tv",
        "episode_count": 55,
        "credit_id": "52579444760ee36aaa707f03",
        "name": "3000 Leagues in Search of Mother",
        "poster_path": "/4htZfAsokFmkTRLFstp2GywDxj0.jpg",
        "original_name": "3000 Leagues in Search of Mother",
        "first_air_date": "1976-01-04",
        "character": "Carlos"
      },
      {
        "id": 8980,
        "media_type": "tv",
        "episode_count": 0,
        "credit_id": "52579481760ee36aaa709e64",
        "name": "Space Carrier Blue Noah",
        "poster_path": "/fykldhPTf4y2spAjSL8jePcSQ9w.jpg",
        "original_name": "Space Carrier Blue Noah",
        "first_air_date": null,
        "character": "Dr. Kenjirō Kusaka"
      },
      {
        "id": 9249,
        "media_type": "tv",
        "episode_count": 0,
        "credit_id": "525795eb760ee36aaa71f78c",
        "name": "Brave Raideen",
        "poster_path": "/qcoNoh10EIpFd9vE46IsMWdYPGY.jpg",
        "original_name": "Brave Raideen",
        "first_air_date": null,
        "character": "Kyuuzou Hibiki"
      },
      {
        "id": 11520,
        "media_type": "tv",
        "episode_count": 52,
        "credit_id": "525810d819c29531db45c08e",
        "name": "Adventures of Pinocchio",
        "poster_path": "/jmVQNFtjQsB3vuAs0lWkb45DURO.jpg",
        "original_name": "Adventures of Pinocchio",
        "first_air_date": null,
        "character": "Old Tree"
      },
      {
        "id": 19411,
        "media_type": "tv",
        "episode_count": 39,
        "credit_id": "52585b15760ee346610fb605",
        "name": "Braiger",
        "poster_path": "/wcKLKrq4M1RvR2O2shtfJlEHcM2.jpg",
        "original_name": "Braiger",
        "first_air_date": "1981-10-06",
        "character": "Dairon"
      },
      {
        "id": 19414,
        "media_type": "tv",
        "episode_count": 0,
        "credit_id": "52585b18760ee346610fb7df",
        "name": "Baxingar",
        "poster_path": null,
        "original_name": "Baxingar",
        "first_air_date": null,
        "character": "Batlle Watkinz"
      },
      {
        "id": 19521,
        "media_type": "tv",
        "episode_count": 49,
        "credit_id": "52585b5e760ee34661101395",
        "name": "The Wonderful Adventures of Nils",
        "poster_path": "/bUphllqRO2Ibh4oyixZ504aykkm.jpg",
        "original_name": "ニルスのふしぎな旅",
        "first_air_date": "1980-01-08",
        "character": "Rosenbaum"
      },
      {
        "id": 19645,
        "media_type": "tv",
        "episode_count": 0,
        "credit_id": "52585bb1760ee34661106405",
        "name": "Baldios",
        "poster_path": "/9KhHIMSnSf6JTBPTNBfC7GYIBsB.jpg",
        "original_name": "Baldios",
        "first_air_date": null,
        "character": "Doctor Raygun"
      },
      {
        "id": 19869,
        "media_type": "tv",
        "episode_count": 39,
        "credit_id": "52585c88760ee34661115f61",
        "name": "La Seine no Hoshi",
        "poster_path": "/f1dVsoyPGNvKgxk1umqe69dfLJF.jpg",
        "original_name": "La Seine no Hoshi",
        "first_air_date": null,
        "character": "Francis, Holy Roman Emperor"
      },
      {
        "id": 20195,
        "media_type": "tv",
        "episode_count": 0,
        "credit_id": "525861e3760ee3466112b0b0",
        "name": "Attack on Tomorrow",
        "poster_path": null,
        "original_name": "Attack on Tomorrow",
        "first_air_date": null,
        "character": ""
      },
      {
        "id": 20611,
        "media_type": "tv",
        "episode_count": 0,
        "credit_id": "525863c1760ee34661156517",
        "name": "Zenderman",
        "poster_path": null,
        "original_name": "Zenderman",
        "first_air_date": null,
        "character": "Dr. Monja"
      },
      {
        "id": 21197,
        "media_type": "tv",
        "episode_count": 0,
        "credit_id": "525865b6760ee3466117d3ce",
        "name": "Musashi, the Samurai Lord",
        "poster_path": null,
        "original_name": "Musashi, the Samurai Lord",
        "first_air_date": null,
        "character": "Takuan"
      },
      {
        "id": 21269,
        "media_type": "tv",
        "episode_count": 52,
        "credit_id": "5258660f760ee34661183048",
        "name": "Superbook",
        "poster_path": "/6oY0ReCpsdjCrNHum2aLOJoWkjp.jpg",
        "original_name": "Superbook",
        "first_air_date": null,
        "character": "Abraham"
      },
      {
        "id": 34158,
        "media_type": "tv",
        "episode_count": 31,
        "credit_id": "5258ac07760ee346616fd134",
        "name": "Magic Knight Rayearth",
        "poster_path": "/dICfVEpRBeJKWXRqH7dKbaSOp45.jpg",
        "original_name": "Magic Knight Rayearth",
        "first_air_date": "1994-10-17",
        "character": "Chang Ang"
      },
      {
        "id": 43715,
        "media_type": "tv",
        "episode_count": 0,
        "credit_id": "525965ad760ee346619af33f",
        "name": "Little Memole",
        "poster_path": null,
        "original_name": "Little Memole",
        "first_air_date": null,
        "character": "Riruru"
      },
      {
        "id": 151,
        "media_type": "tv",
        "episode_count": 26,
        "credit_id": "52533efd19c295794008afd4",
        "name": "Bosco Adventure",
        "poster_path": null,
        "original_name": "Bosco Adventure",
        "first_air_date": "1986-10-06",
        "character": "Ender"
      },
      {
        "id": 151,
        "media_type": "tv",
        "episode_count": 26,
        "credit_id": "52533f0419c295794008b270",
        "name": "Bosco Adventure",
        "poster_path": null,
        "original_name": "Bosco Adventure",
        "first_air_date": "1986-10-06",
        "character": "Owl"
      },
      {
        "id": 20525,
        "media_type": "tv",
        "episode_count": 0,
        "credit_id": "52586361760ee3466114b270",
        "name": "Getter Robo Go",
        "poster_path": null,
        "original_name": "Getter Robo Go",
        "first_air_date": null,
        "character": "Doctor Yoshii"
      },
      {
        "id": 21618,
        "media_type": "tv",
        "episode_count": 0,
        "credit_id": "52586a67760ee346611ab70c",
        "name": "Little Women",
        "poster_path": "/mvGuAPX1USVM5Xx0JHzvEBKk1c8.jpg",
        "original_name": "Little Women",
        "first_air_date": null,
        "character": "James"
      },
      {
        "id": 23591,
        "media_type": "tv",
        "episode_count": 30,
        "credit_id": "5258737e760ee346612644d3",
        "name": "Charlotte of the Young Grass",
        "poster_path": null,
        "original_name": "Charlotte of the Young Grass",
        "first_air_date": null,
        "character": "Count"
      },
      {
        "id": 30591,
        "media_type": "tv",
        "episode_count": 52,
        "credit_id": "525898db760ee346615c7aaf",
        "name": "Alps no Shoujo Heidi",
        "poster_path": null,
        "original_name": "Alps no Shoujo Heidi",
        "first_air_date": null,
        "character": ""
      },
      {
        "id": 34797,
        "media_type": "tv",
        "episode_count": 1,
        "credit_id": "5258dafb760ee346617420fe",
        "name": "Tokimeki Tonight",
        "poster_path": "/6bGb1bTWRj8DH7HmQENfc8cdHd0.jpg",
        "original_name": "Tokimeki Tonight",
        "first_air_date": "1982-10-06",
        "character": ""
      },
      {
        "id": 43930,
        "media_type": "tv",
        "episode_count": 0,
        "credit_id": "52596641760ee346619b6f88",
        "name": "King Arthur",
        "poster_path": null,
        "original_name": "King Arthur",
        "first_air_date": null,
        "character": "Archbishop"
      },
      {
        "id": 45002,
        "media_type": "tv",
        "episode_count": 0,
        "credit_id": "52596988760ee346619e0a76",
        "name": "Heidi, Girl of the Alps",
        "poster_path": null,
        "original_name": "Heidi, Girl of the Alps",
        "first_air_date": null,
        "character": "Heidi's Grandfather"
      },
      {
        "id": 12971,
        "media_type": "tv",
        "episode_count": 291,
        "credit_id": "525824cd760ee36aaa7f239a",
        "name": "Dragon Ball Z",
        "poster_path": "/yS7axjtRXTbvqLJWPVsjMXzNBZb.jpg",
        "original_name": "Dragon Ball Z",
        "first_air_date": "1989-04-26",
        "character": "Master Roshi"
      }
    ],
    "crew": []
  },
  "name": "Kōhei Miyauchi",
  "place_of_birth": null,
  "popularity": "1.03375000022228"
}