{
  "budget": 25000000,
  "vote_average": 6.2,
  "backdrop_path": "/o15nLGxWouLZgCexzSE2ybyBToV.jpg",
  "genres": [
    {
      "id": 35,
      "name": "Comedy"
    },
    {
      "id": 18,
      "name": "Drama"
    },
    {
      "id": 10749,
      "name": "Romance"
    }
  ],
  "status": "Released",
  "credits": {
    "cast": [
      {
        "id": 9137,
        "order": 0,
        "credit_id": "52fe4261c3a36847f8019e7f",
        "name": "Renée Zellweger",
        "cast_id": 1,
        "profile_path": "/rAfHyC0IxqwRTKuwosU85ZwQicL.jpg",
        "character": "Bridget Jones"
      },
      {
        "id": 5472,
        "order": 1,
        "credit_id": "52fe4261c3a36847f8019f0d",
        "name": "Colin Firth",
        "cast_id": 40,
        "profile_path": "/4pj31PUxqpuJZrHChinub4gr2ul.jpg",
        "character": "Mark Darcy"
      },
      {
        "id": 3291,
        "order": 2,
        "credit_id": "52fe4261c3a36847f8019f11",
        "name": "Hugh Grant",
        "cast_id": 41,
        "profile_path": "/r3rSJLJwKmsJyPA3gojzuMthJ4C.jpg",
        "character": "Daniel Cleaver"
      },
      {
        "id": 9138,
        "order": 3,
        "credit_id": "52fe4261c3a36847f8019f15",
        "name": "Gemma Jones",
        "cast_id": 42,
        "profile_path": "/8kTbA92LoY0l76SeDeanC5vb6iB.jpg",
        "character": "Bridget's Mum"
      },
      {
        "id": 388,
        "order": 4,
        "credit_id": "52fe4261c3a36847f8019f19",
        "name": "Jim Broadbent",
        "cast_id": 43,
        "profile_path": "/xWR0M9yaqcc6neBAg8tMgqGXwS3.jpg",
        "character": "Bridget's Dad"
      },
      {
        "id": 9145,
        "order": 5,
        "credit_id": "52fe4261c3a36847f8019f1d",
        "name": "James Callis",
        "cast_id": 44,
        "profile_path": "/eKYhq4PGfqE7F2xOjNyeyXHNhRU.jpg",
        "character": "Tom"
      },
      {
        "id": 9144,
        "order": 6,
        "credit_id": "52fe4261c3a36847f8019f21",
        "name": "Sally Phillips",
        "cast_id": 45,
        "profile_path": "/cr0fXU9N69QOcBNZ98ih5A6QbTr.jpg",
        "character": "Shazza"
      },
      {
        "id": 1834,
        "order": 7,
        "credit_id": "52fe4261c3a36847f8019f25",
        "name": "Shirley Henderson",
        "cast_id": 46,
        "profile_path": "/yxFCumQ2vjMgpdENmroOFN6KENO.jpg",
        "character": "Jude"
      },
      {
        "id": 6368,
        "order": 8,
        "credit_id": "52fe4261c3a36847f8019f29",
        "name": "Embeth Davidtz",
        "cast_id": 47,
        "profile_path": "/gmc4nZtGc6bge9DnriR57VYq0dA.jpg",
        "character": "Natasha"
      },
      {
        "id": 9146,
        "order": 9,
        "credit_id": "52fe4261c3a36847f8019f2d",
        "name": "Lisa Barbuscia",
        "cast_id": 48,
        "profile_path": "/fesKDQexfUIPI3NYDhIKa6Vfe66.jpg",
        "character": "Lara"
      }
    ],
    "crew": [
      {
        "id": 9148,
        "credit_id": "52fe4261c3a36847f8019e85",
        "department": "Production",
        "name": "Brian Donovan",
        "job": "Production Supervisor",
        "profile_path": null
      },
      {
        "id": 5489,
        "credit_id": "52fe4261c3a36847f8019e8b",
        "department": "Production",
        "name": "Michelle Guish",
        "job": "Casting",
        "profile_path": null
      },
      {
        "id": 9149,
        "credit_id": "52fe4261c3a36847f8019e91",
        "department": "Production",
        "name": "Peter McAleese",
        "job": "Line Producer",
        "profile_path": null
      },
      {
        "id": 9150,
        "credit_id": "52fe4261c3a36847f8019e97",
        "department": "Production",
        "name": "Debra Hayward",
        "job": "Producer",
        "profile_path": null
      },
      {
        "id": 9151,
        "credit_id": "52fe4261c3a36847f8019e9d",
        "department": "Production",
        "name": "Liza Chasin",
        "job": "Producer",
        "profile_path": null
      },
      {
        "id": 9152,
        "credit_id": "52fe4261c3a36847f8019ea3",
        "department": "Sound",
        "name": "Patrick Doyle",
        "job": "Original Music Composer",
        "profile_path": null
      },
      {
        "id": 9153,
        "credit_id": "52fe4261c3a36847f8019ea9",
        "department": "Art",
        "name": "Gemma Jackson",
        "job": "Production Design",
        "profile_path": null
      },
      {
        "id": 9154,
        "credit_id": "52fe4261c3a36847f8019eaf",
        "department": "Editing",
        "name": "Martin Walsh",
        "job": "Editor",
        "profile_path": null
      },
      {
        "id": 7262,
        "credit_id": "52fe4261c3a36847f8019eb5",
        "department": "Camera",
        "name": "Stuart Dryburgh",
        "job": "Director of Photography",
        "profile_path": null
      },
      {
        "id": 9155,
        "credit_id": "52fe4261c3a36847f8019ebb",
        "department": "Production",
        "name": "Helen Fielding",
        "job": "Executive Producer",
        "profile_path": null
      },
      {
        "id": 9155,
        "credit_id": "52fe4261c3a36847f8019ec1",
        "department": "Writing",
        "name": "Helen Fielding",
        "job": "Novel",
        "profile_path": null
      },
      {
        "id": 9155,
        "credit_id": "52fe4261c3a36847f8019ec7",
        "department": "Writing",
        "name": "Helen Fielding",
        "job": "Screenplay",
        "profile_path": null
      },
      {
        "id": 9156,
        "credit_id": "52fe4261c3a36847f8019ecd",
        "department": "Writing",
        "name": "Andrew Davies",
        "job": "Screenplay",
        "profile_path": null
      },
      {
        "id": 7018,
        "credit_id": "52fe4261c3a36847f8019ed3",
        "department": "Writing",
        "name": "Richard Curtis",
        "job": "Screenplay",
        "profile_path": "/uLjkovqtUtM4SckCFtrevZKKJNM.jpg"
      },
      {
        "id": 2236,
        "credit_id": "52fe4261c3a36847f8019ed9",
        "department": "Production",
        "name": "Tim Bevan",
        "job": "Producer",
        "profile_path": null
      },
      {
        "id": 2238,
        "credit_id": "52fe4261c3a36847f8019edf",
        "department": "Production",
        "name": "Eric Fellner",
        "job": "Producer",
        "profile_path": null
      },
      {
        "id": 9157,
        "credit_id": "52fe4261c3a36847f8019ee5",
        "department": "Production",
        "name": "Jonathan Cavendish",
        "job": "Producer",
        "profile_path": null
      },
      {
        "id": 9158,
        "credit_id": "52fe4261c3a36847f8019eeb",
        "department": "Directing",
        "name": "Sharon Maguire",
        "job": "Director",
        "profile_path": "/oy9U1x6801cocQT5uQNhLvrCCtc.jpg"
      },
      {
        "id": 9159,
        "credit_id": "52fe4261c3a36847f8019ef1",
        "department": "Sound",
        "name": "David Crozier",
        "job": "Sound mixer",
        "profile_path": null
      },
      {
        "id": 9160,
        "credit_id": "52fe4261c3a36847f8019ef7",
        "department": "Sound",
        "name": "Michael Higham",
        "job": "Music Editor",
        "profile_path": null
      },
      {
        "id": 9161,
        "credit_id": "52fe4261c3a36847f8019efd",
        "department": "Costume & Make-Up",
        "name": "Carmel Jackson",
        "job": "Makeup Artist",
        "profile_path": null
      },
      {
        "id": 9162,
        "credit_id": "52fe4261c3a36847f8019f03",
        "department": "Costume & Make-Up",
        "name": "Lorna McGowan",
        "job": "Makeup Artist",
        "profile_path": null
      },
      {
        "id": 9006,
        "credit_id": "52fe4261c3a36847f8019f09",
        "department": "Costume & Make-Up",
        "name": "Rachael Fleming",
        "job": "Costume Design",
        "profile_path": null
      }
    ]
  },
  "runtime": 97,
  "spoken_languages": [{
    "iso_639_1": "en",
    "name": "English"
  }],
  "adult": false,
  "homepage": "",
  "id": 634,
  "production_countries": [
    {
      "name": "France",
      "iso_3166_1": "FR"
    },
    {
      "name": "United Kingdom",
      "iso_3166_1": "GB"
    },
    {
      "name": "Ireland",
      "iso_3166_1": "IE"
    },
    {
      "name": "United States of America",
      "iso_3166_1": "US"
    }
  ],
  "title": "Bridget Jones's Diary",
  "overview": "Bridget Jones\u2019s Diary is a romantic love story comedy from the best selling novel of the same name by Helen Fielding. A chaotic Jones meets a snobbish lawer named Marc and soon he enters into her world of imperfections.",
  "production_companies": [
    {
      "id": 14,
      "name": "Miramax Films"
    },
    {
      "id": 33,
      "name": "Universal Pictures"
    },
    {
      "id": 5870,
      "name": "Studio Canal"
    },
    {
      "id": 10163,
      "name": "Working Title Films"
    },
    {
      "id": 11358,
      "name": "Little Bird"
    }
  ],
  "belongs_to_collection": {
    "id": 8936,
    "backdrop_path": "/jiS4x140miaEH524CAFTvuxrcZ1.jpg",
    "name": "Bridget Jones",
    "poster_path": "/uUYWnkgtebGDQ63NaLZfGPON95P.jpg"
  },
  "imdb_id": "tt0243155",
  "release_date": "2001-03-13",
  "original_title": "Bridget Jones's Diary",
  "vote_count": 159,
  "poster_path": "/bSr5bdlAumfBWCibvMLvhvMEkkB.jpg",
  "tagline": "Health Warning: Adopting Bridget's lifestyle could seriously damage your health.",
  "revenue": 281929795,
  "popularity": "1.60550558802737"
}