{
  "budget": 7000000,
  "vote_average": 6.2,
  "backdrop_path": "/o71ywQSmQ1hNPSLKJuCMyDTrL7K.jpg",
  "genres": [
    {
      "id": 28,
      "name": "Action"
    },
    {
      "id": 12,
      "name": "Adventure"
    },
    {
      "id": 53,
      "name": "Thriller"
    }
  ],
  "status": "Released",
  "credits": {
    "cast": [
      {
        "id": 10167,
        "order": 0,
        "credit_id": "52fe4267c3a36847f801bc3b",
        "name": "George Lazenby",
        "cast_id": 1,
        "profile_path": "/xjVF7SwzjRkTB45eMqNLefUFyg0.jpg",
        "character": "James Bond"
      },
      {
        "id": 10168,
        "order": 1,
        "credit_id": "52fe4267c3a36847f801bc3f",
        "name": "Diana Rigg",
        "cast_id": 2,
        "profile_path": "/sq1piruQQIv3RoWwDGQmT6x6f6Z.jpg",
        "character": "Tracy Di Vicenzo"
      },
      {
        "id": 10169,
        "order": 2,
        "credit_id": "52fe4267c3a36847f801bc43",
        "name": "Telly Savalas",
        "cast_id": 3,
        "profile_path": "/37s6uJijtMcxqA0wQEZC2YyVsSl.jpg",
        "character": "Ernst Stavro Blofeld"
      },
      {
        "id": 4961,
        "order": 3,
        "credit_id": "52fe4267c3a36847f801bc47",
        "name": "Gabriele Ferzetti",
        "cast_id": 4,
        "profile_path": "/gpiJIBogUvPgKIwf65BXu37NDY1.jpg",
        "character": "Marc Ange Draco"
      },
      {
        "id": 10170,
        "order": 4,
        "credit_id": "52fe4267c3a36847f801bc4b",
        "name": "Ilse Steppat",
        "cast_id": 5,
        "profile_path": "/8RhUsZYeQR8R5ic5vwGqYc9VkL.jpg",
        "character": "Irma Bunt"
      },
      {
        "id": 10171,
        "order": 5,
        "credit_id": "52fe4267c3a36847f801bc4f",
        "name": "Angela Scoular",
        "cast_id": 6,
        "profile_path": "/86R3qYBBMP7hPjCUaQaLbznXBN0.jpg",
        "character": "Ruby Bartlett"
      },
      {
        "id": 9878,
        "order": 6,
        "credit_id": "52fe4267c3a36847f801bc53",
        "name": "Lois Maxwell",
        "cast_id": 7,
        "profile_path": "/uQneO3fT5H7vmjxusi3lJmm3xT3.jpg",
        "character": "Miss Moneypenny"
      },
      {
        "id": 10173,
        "order": 8,
        "credit_id": "52fe4267c3a36847f801bc57",
        "name": "George Baker",
        "cast_id": 9,
        "profile_path": "/ogT7DAofS8SqeaZlQQSmJcn2sN8.jpg",
        "character": "Sir Hilary Bray"
      },
      {
        "id": 9874,
        "order": 9,
        "credit_id": "52fe4267c3a36847f801bc5b",
        "name": "Bernard Lee",
        "cast_id": 10,
        "profile_path": "/vCLXqcJNAijcVrRrJuoduc5VnSd.jpg",
        "character": "M"
      },
      {
        "id": 9906,
        "order": 10,
        "credit_id": "52fe4267c3a36847f801bc5f",
        "name": "Desmond Llewelyn",
        "cast_id": 12,
        "profile_path": "/kJxILFKzFPSVVkpVsCOW7BWFVfy.jpg",
        "character": "Q"
      },
      {
        "id": 18915,
        "order": 11,
        "credit_id": "52fe4267c3a36847f801bcb1",
        "name": "Catherine Schell",
        "cast_id": 28,
        "profile_path": "/y4czs0CUCf4z2XAQT3C1yzXWdPD.jpg",
        "character": "Nancy"
      }
    ],
    "crew": [
      {
        "id": 9868,
        "credit_id": "52fe4267c3a36847f801bc65",
        "department": "Directing",
        "name": "Peter R. Hunt",
        "job": "Director",
        "profile_path": null
      },
      {
        "id": 9856,
        "credit_id": "52fe4267c3a36847f801bc6b",
        "department": "Writing",
        "name": "Ian Fleming",
        "job": "Novel",
        "profile_path": "/91U37Em6Ru87DiAPMdsocGKyQ0W.jpg"
      },
      {
        "id": 9858,
        "credit_id": "52fe4267c3a36847f801bc71",
        "department": "Writing",
        "name": "Richard Maibaum",
        "job": "Screenplay",
        "profile_path": null
      },
      {
        "id": 9861,
        "credit_id": "52fe4267c3a36847f801bc77",
        "department": "Production",
        "name": "Albert R. Broccoli",
        "job": "Producer",
        "profile_path": "/bgYayDE2fRsgF3ytSzbWvdkDejJ.jpg"
      },
      {
        "id": 9863,
        "credit_id": "52fe4267c3a36847f801bc7d",
        "department": "Production",
        "name": "Harry Saltzman",
        "job": "Producer",
        "profile_path": null
      },
      {
        "id": 10177,
        "credit_id": "52fe4267c3a36847f801bc83",
        "department": "Production",
        "name": "Stanley Sopel",
        "job": "Producer",
        "profile_path": null
      },
      {
        "id": 2289,
        "credit_id": "52fe4267c3a36847f801bc89",
        "department": "Sound",
        "name": "John Barry",
        "job": "Original Music Composer",
        "profile_path": "/hcKxefFH5M6euZfJ8h0WJnEYMHa.jpg"
      },
      {
        "id": 10178,
        "credit_id": "52fe4267c3a36847f801bc8f",
        "department": "Camera",
        "name": "Michael Reed",
        "job": "Director of Photography",
        "profile_path": null
      },
      {
        "id": 10179,
        "credit_id": "52fe4267c3a36847f801bc95",
        "department": "Editing",
        "name": "John Glen",
        "job": "Editor",
        "profile_path": null
      },
      {
        "id": 7756,
        "credit_id": "52fe4267c3a36847f801bc9b",
        "department": "Art",
        "name": "Syd Cain",
        "job": "Production Design",
        "profile_path": null
      },
      {
        "id": 8524,
        "credit_id": "52fe4267c3a36847f801bca1",
        "department": "Art",
        "name": "Peter Lamont",
        "job": "Set Decoration",
        "profile_path": null
      },
      {
        "id": 10181,
        "credit_id": "52fe4267c3a36847f801bca7",
        "department": "Costume & Make-Up",
        "name": "Marjory Cornelius",
        "job": "Costume Design",
        "profile_path": null
      },
      {
        "id": 7757,
        "credit_id": "52fe4267c3a36847f801bcad",
        "department": "Art",
        "name": "Robert W. Laing",
        "job": "Art Direction",
        "profile_path": null
      }
    ]
  },
  "runtime": 142,
  "spoken_languages": [
    {
      "iso_639_1": "en",
      "name": "English"
    },
    {
      "iso_639_1": "de",
      "name": "Deutsch"
    }
  ],
  "adult": false,
  "homepage": "http://www.mgm.com/view/movie/1411/On-Her-Majesty%E2%80%99s-Secret-Service/",
  "id": 668,
  "production_countries": [
    {
      "name": "United Kingdom",
      "iso_3166_1": "GB"
    },
    {
      "name": "United States of America",
      "iso_3166_1": "US"
    }
  ],
  "title": "On Her Majesty's Secret Service",
  "overview": "James Bond tracks archnemesis Ernst Blofeld to a mountaintop retreat where he's training an army of beautiful but lethal women. Along the way, Bond falls for Italian contessa Tracy Draco -- and marries her in order to get closer to Blofeld. Meanwhile, he locates Blofeld in the Alps and embarks on a classic ski chase.",
  "production_companies": [
    {
      "id": 21,
      "name": "Metro-Goldwyn-Mayer"
    },
    {
      "id": 7576,
      "name": "Eon Productions"
    },
    {
      "id": 10761,
      "name": "Danjaq"
    }
  ],
  "belongs_to_collection": {
    "id": 645,
    "backdrop_path": "/v57QgSTbbiN33sshS1AS0QDcPC2.jpg",
    "name": "James Bond Collection",
    "poster_path": "/ckNgEItskTZHeTySYfGvageRFSq.jpg"
  },
  "imdb_id": "tt0064757",
  "release_date": "1969-12-18",
  "original_title": "On Her Majesty's Secret Service",
  "vote_count": 98,
  "poster_path": "/sd1OYYEsfH8I6X3n8DrqpDgeXBA.jpg",
  "tagline": "Far up! Far out! Far more! James Bond 007 is back!",
  "revenue": 81974493,
  "popularity": "1.77307350046265"
}